MyoQMRI/__about__.py
MyoQMRI/__init__.py
MyoQMRI/bin/__init__.py
MyoQMRI/bin/fatwater.py
MyoQMRI/bin/raw2nii_pulseq_mese_leg.py
MyoQMRI/bin/waterT2.py
MyoQMRI/bin/write_pulseq_mese_leg.py
MyoQMRI/fatwater/__init__.py
MyoQMRI/fatwater/fatwater.py
MyoQMRI/mese_pulseq/__init__.py
MyoQMRI/mese_pulseq/mese_leg.json
MyoQMRI/mese_pulseq/mese_leg.seq
MyoQMRI/mese_pulseq/raw2nii_pulseq_mese_leg.py
MyoQMRI/mese_pulseq/write_pulseq_mese_leg.py
MyoQMRI/waterT2/FatFractionLookup.py
MyoQMRI/waterT2/FatFractionLookup_GPU.py
MyoQMRI/waterT2/SlrTransform.py
MyoQMRI/waterT2/__init__.py
MyoQMRI/waterT2/epg.cu
MyoQMRI/waterT2/epg_sim.py
MyoQMRI/waterT2/findmax_ff.cu
MyoQMRI/waterT2/findmax_ff.py
MyoQMRI/waterT2/padorcut.py
MyoQMRI/waterT2/registerDatasets.py
MyoQMRI/waterT2/waterT2.py
myoqmri-2.0.2.dist-info/METADATA
myoqmri-2.0.2.dist-info/WHEEL
myoqmri-2.0.2.dist-info/entry_points.txt
myoqmri-2.0.2.dist-info/licenses/LICENSE
myoqmri-2.0.2.dist-info/RECORD
