Metadata-Version: 2.4
Name: MyoQMRI
Version: 2.0.2
Summary: A package for quantitative analysis of muscle MRI
Project-URL: Repository, https://github.com/bammri/MyoQMRI
Author-email: Jessica Schäper <jessica.schaeper@unibas.ch>, Francesco Santini <francesco.santini@unibas.ch>
License-Expression: GPL-3.0-only
License-File: LICENSE
Classifier: Operating System :: OS Independent
Classifier: Programming Language :: Python :: 3
Requires-Python: >=3.9
Requires-Dist: matplotlib
Requires-Dist: nibabel
Requires-Dist: numpy
Requires-Dist: ormir-mids>=0.1.2
Requires-Dist: progress
Requires-Dist: pydicom
Requires-Dist: pymapvbvd
Requires-Dist: pypulseq==1.4.2
Requires-Dist: scipy
Requires-Dist: sigpy
Requires-Dist: twixtools
Provides-Extra: cuda
Requires-Dist: pycuda; extra == 'cuda'
Requires-Dist: scikit-cuda; extra == 'cuda'
Provides-Extra: elastix
Requires-Dist: simpleitk-simpleelastix; extra == 'elastix'
